topsis_jivitesh_102303229/__init__.py
topsis_jivitesh_102303229/cli.py
topsis_jivitesh_102303229/topsis.py
topsis_jivitesh_102303229-0.1.0.dist-info/licenses/LICENSE
topsis_jivitesh_102303229-0.1.0.dist-info/METADATA
topsis_jivitesh_102303229-0.1.0.dist-info/WHEEL
topsis_jivitesh_102303229-0.1.0.dist-info/entry_points.txt
topsis_jivitesh_102303229-0.1.0.dist-info/top_level.txt
topsis_jivitesh_102303229-0.1.0.dist-info/RECORD
