Metadata-Version: 2.4
Name: Topsis-Jivitesh-102303229
Version: 0.1.0
Summary: TOPSIS implementation
Author: Jivitesh
Author-email: jiviteshsinghahluwalia@gmail.com
License: MIT
License-File: LICENSE
Requires-Dist: numpy
Requires-Dist: pandas
Dynamic: license-file
